setup.py
distributions_1991/Binomialdistribution.py
distributions_1991/Gaussiandistribution.py
distributions_1991/Generaldistribution.py
distributions_1991/__init__.py
distributions_1991.egg-info/PKG-INFO
distributions_1991.egg-info/SOURCES.txt
distributions_1991.egg-info/dependency_links.txt
distributions_1991.egg-info/not-zip-safe
distributions_1991.egg-info/top_level.txt